README.md
pyproject.toml
setup.py
cian/__init__.py
cian/client.py
cian/constants.py
cian/exceptions.py
cian.egg-info/PKG-INFO
cian.egg-info/SOURCES.txt
cian.egg-info/dependency_links.txt
cian.egg-info/requires.txt
cian.egg-info/top_level.txt