Metadata-Version: 2.1
Name: cian
Version: 0.1.1
Summary: Sync/async library for searching offers on Cian
Home-page: https://github.com/OlegYurchik/cian
Author: Oleg Yurchik
Author-email: oleg.yurchik@protonmail.com
License: UNKNOWN
Platform: UNKNOWN
